ndexr_reddit/__init__.py
ndexr_reddit/subreddits.py
ndexr_reddit-0.0.2.dist-info/LICENSE
ndexr_reddit-0.0.2.dist-info/METADATA
ndexr_reddit-0.0.2.dist-info/WHEEL
ndexr_reddit-0.0.2.dist-info/top_level.txt
ndexr_reddit-0.0.2.dist-info/RECORD
