Metadata-Version: 2.1
Name: ndexr-reddit
Version: 0.0.2
Summary: A simple package for gathering Reddit data
Home-page: http://github.com/fdrennan/ndexr_reddit
Author: Freddy Drennan
Author-email: drennanfreddy@gmail.com
License: UNKNOWN
Keywords: package numbers calculations
Platform: UNKNOWN
Classifier: Programming Language :: Python :: 3
Classifier: Operating System :: OS Independent
Requires-Python: >=3.4
Requires-Dist: praw
Requires-Dist: pandas
